{
  "cart": {
    "id": "10",
    "shop_id": "1",
    "stream_id": "npwQThnx",
    "on_air": "1",
    "product_id": "0",
    "title": "FlexiTwist B-6616 C8 Frame - Brown",
    "description": "This nearly indestructible frame is the only Eye Glass frame in the world that is flexible, yet looks like any fashion acetate style. FlexiTwist is made from an innocative Swiss technology. This memory thermoplastic is the material used in all of our FlexiTwist glasses. FlexiTwists durability is a by-product of...",
    "price": "38 UAH",
    "price_origin": "38 UAH",
    "image": "https:\/\/cdn.shopify.com\/s\/files\/1\/1789\/6505\/products\/FlexiTwist_B-6616_C8_Brown_a.jpg?v=1491810385",
    "link": "https:\/\/makebecool-on-shopify.myshopify.com\/products\/flexitwist-b-6616-c8-frame"
  }
}
